cronsim/__init__.py
cronsim/cronsim.py
cronsim/explain.py
cronsim/py.typed
cronsim-2.6.dist-info/LICENSE
cronsim-2.6.dist-info/METADATA
cronsim-2.6.dist-info/WHEEL
cronsim-2.6.dist-info/top_level.txt
cronsim-2.6.dist-info/RECORD
