Metadata-Version: 2.1
Name: cronsim
Version: 2.6
Summary: Cron expression parser and evaluator
Home-page: https://github.com/cuu508/cronsim
Author: Pēteris Caune
Author-email: cuu508@monkeyseemonkeydo.lv
License: BSD
Project-URL: Changelog, https://github.com/cuu508/cronsim/blob/main/CHANGELOG.md
Keywords: cron,cronjob,crontab,schedule
Platform: any
Classifier: Development Status :: 5 - Production/Stable
Classifier: Intended Audience :: Developers
Classifier: License :: OSI Approved :: BSD License
Classifier: Operating System :: OS Independent
Classifier: Programming Language :: Python
Classifier: Programming Language :: Python :: 3
Classifier: Topic :: Software Development :: Libraries :: Python Modules
Requires-Python: >= 3.8
License-File: LICENSE
